LICENSE
MANIFEST.in
README.rst
setup.py
lice/__init__.py
lice/core.py
lice/template-afl3.txt
lice/template-agpl3-header.txt
lice/template-agpl3.txt
lice/template-apache-header.txt
lice/template-apache.txt
lice/template-bsd2.txt
lice/template-bsd3.txt
lice/template-cc0-header.txt
lice/template-cc0.txt
lice/template-cc_by-header.txt
lice/template-cc_by.txt
lice/template-cc_by_nc-header.txt
lice/template-cc_by_nc.txt
lice/template-cc_by_nc_nd-header.txt
lice/template-cc_by_nc_nd.txt
lice/template-cc_by_nc_sa-header.txt
lice/template-cc_by_nc_sa.txt
lice/template-cc_by_nd-header.txt
lice/template-cc_by_nd.txt
lice/template-cc_by_sa-header.txt
lice/template-cc_by_sa.txt
lice/template-cddl.txt
lice/template-epl.txt
lice/template-gpl2-header.txt
lice/template-gpl2.txt
lice/template-gpl3-header.txt
lice/template-gpl3.txt
lice/template-isc.txt
lice/template-lgpl.txt
lice/template-mit.txt
lice/template-mpl-header.txt
lice/template-mpl.txt
lice/template-wtfpl-header.txt
lice/template-wtfpl.txt
lice/template-zlib.txt
lice.egg-info/PKG-INFO
lice.egg-info/SOURCES.txt
lice.egg-info/dependency_links.txt
lice.egg-info/entry_points.txt
lice.egg-info/top_level.txt
lice/tests/__init__.py
lice/tests/test_lice.py