Metadata-Version: 1.1
Name: lice
Version: 0.6
Summary: Generate a license file for a project
Home-page: https://github.com/licenses/lice
Author: Jeremy Carbaugh
Author-email: jcarbaugh@gmail.com
License: BSD
Platform: any
Classifier: Development Status :: 4 - Beta
Classifier: License :: OSI Approved :: BSD License
Classifier: Intended Audience :: Developers
Classifier: Operating System :: OS Independent
Classifier: Programming Language :: Python
Classifier: Programming Language :: Python :: 3
